llmax/__init__.py
llmax/__main__.py
llmax/clients/__init__.py
llmax/clients/multi_ai_client.py
llmax/external_clients/__init__.py
llmax/external_clients/anthropic.py
llmax/external_clients/clients.py
llmax/external_clients/cohere.py
llmax/external_clients/exceptions.py
llmax/external_clients/gemini.py
llmax/external_clients/grok.py
llmax/external_clients/meta.py
llmax/external_clients/mistral.py
llmax/external_clients/openai.py
llmax/external_clients/scaleway.py
llmax/external_clients/universal_client/__init__.py
llmax/external_clients/universal_client/chat.py
llmax/external_clients/universal_client/chat_completion_message.py
llmax/external_clients/universal_client/client.py
llmax/external_clients/universal_client/completions.py
llmax/external_clients/whisper.py
llmax/messages/__init__.py
llmax/messages/message.py
llmax/messages/messages.py
llmax/models/__init__.py
llmax/models/deployment.py
llmax/models/fake.py
llmax/models/models.py
llmax/models/providers.py
llmax/py.typed
llmax/usage/__init__.py
llmax/usage/exceptions.py
llmax/usage/prices.py
llmax/usage/tokens.py
llmax/usage/usage.py
llmax/utils/__init__.py
llmax/utils/logger.py
llmax/utils/types.py
delos_llmax-1.13.3.dist-info/METADATA
delos_llmax-1.13.3.dist-info/WHEEL
delos_llmax-1.13.3.dist-info/licenses/LICENSE
delos_llmax-1.13.3.dist-info/RECORD
