Metadata-Version: 2.4
Name: delos-llmax
Version: 1.13.3
Summary: Interface to handle multiple LLMs and AI tools.
License-File: LICENSE
Keywords: AI,LLM,generative
Author: Delos Intelligence
Author-email: maximiliendedinechin@delosintelligence.fr
Requires-Python: >=3.10,<4.0
Classifier: Programming Language :: Python :: 3
Classifier: Programming Language :: Python :: 3.10
Classifier: Programming Language :: Python :: 3.11
Classifier: Programming Language :: Python :: 3.12
Classifier: Programming Language :: Python :: 3.13
Classifier: Programming Language :: Python :: 3.14
Requires-Dist: boto3 (>=1.35.65,<2.0.0)
Requires-Dist: google-auth (>=2.36.0,<3.0.0)
Requires-Dist: google-genai (==1.2.0)
Requires-Dist: loguru (>=0.7.2,<0.8.0)
Requires-Dist: openai (>=1.42.0,<2.0.0)
Requires-Dist: pydantic (>=2.9.2,<3.0.0)
Requires-Dist: pydub (>=0.25.1,<0.26.0)
Requires-Dist: python-dotenv (>=1.0.1,<2.0.0)
Requires-Dist: tiktoken (>=0.7.0,<0.8.0)
